xinfcli/api/__init__.py
xinfcli/api/inference_request.py
xinfcli/api/inference_response.py
xinfcli/api/interface.py
xinfcli/config_classes/__init__.py
xinfcli/config_classes/network.py
xinfcli/model_utils/__init__.py
xinfcli/model_utils/data_type.py
xinfcli/model_utils/model_config.py
xinfcli/model_utils/tensor.py
xinfcli/utils/__init__.py
xinfcli/utils/archive.py
xinfcli/utils/async_executor.py
xinfcli/utils/config.py
xinfcli/utils/pbtxt.py
xinfcli-0.1.dist-info/METADATA
xinfcli-0.1.dist-info/WHEEL
xinfcli-0.1.dist-info/RECORD
