Metadata-Version: 2.3
Name: xinfcli
Version: 0.1
Summary: A simple client for inference.
Project-URL: Homepage, https://github.com
Project-URL: Issues, https://github.com
Author-email: Kotenokov <kotenokov@gmail.com>
Classifier: Intended Audience :: Developers
Classifier: Programming Language :: Python :: 3.8
Requires-Python: >=3.8
Requires-Dist: aiohttp>=3.8.4
Requires-Dist: numpy>=1.22.2
